{
  "title": "Modifications",
  "url": "https://starscape-roblox.fandom.com/en/wiki/Modifications",
  "summary": "This is about the stat upgrade modules for ships. for turrets, click here.",
  "full_text": "Modifications\nThis is about the stat upgrade modules for ships. for turrets, click here.\nModules are items that can be applied to a ship to change its statistics and abilities.\nThere are two types of modules: \nRigs are always-active upgrades that affect your ship's statistics at all times. \nSubsystems are abilities that can be activated and only affect statistics for a limited time while they are active before a cooldown.",
  "content_structure": {
    "title": "Modifications",
    "content": "This is about the stat upgrade modules for ships. for turrets, click here.\nModules are items that can be applied to a ship to change its statistics and abilities.\nThere are two types of modules: \nRigs are always-active upgrades that affect your ship's statistics at all times. \nSubsystems are abilities that can be activated and only affect statistics for a limited time while they are active before a cooldown."
  },
  "images": []
}